atolldb/__init__.py
atolldb/database.py
atolldb/index.acc_num.txt
atolldb/io.py
atolldb/island.py
atolldb/parsing/__init__.py
atolldb/parsing/html.py
atolldb/parsing/islander_db.py
atolldb/parsing/mysql2sqlite
atolldb/parsing/sql.py
atolldb/parsing/text.py
atolldb/utils.py
atolldb-0.1.0.dist-info/WHEEL
atolldb-0.1.0.dist-info/METADATA
atolldb-0.1.0.dist-info/RECORD
